pyxpad/__init__.py
pyxpad/__main__.py
pyxpad/_version.py
pyxpad/boutsource.py
pyxpad/calculus.py
pyxpad/configdialog.py
pyxpad/console_widget.py
pyxpad/datafile.py
pyxpad/fourier.py
pyxpad/matplotlib_widget.py
pyxpad/mock_data.py
pyxpad/pyxpad.py
pyxpad/pyxpad_main.py
pyxpad/pyxpad_utils.py
pyxpad/read_idl.py
pyxpad/user_functions.py
pyxpad/xpadsource.py
pyxpad-0.6.0.dist-info/COPYING
pyxpad-0.6.0.dist-info/METADATA
pyxpad-0.6.0.dist-info/WHEEL
pyxpad-0.6.0.dist-info/entry_points.txt
pyxpad-0.6.0.dist-info/top_level.txt
pyxpad-0.6.0.dist-info/RECORD
