Metadata-Version: 2.1
Name: pyxpad
Version: 0.6.0
Summary: "Data visualisation and analysis tool for IDAM",
Home-page: https://github.com/ZedThree/pyxpad/
Author: Ben Dudson
Author-email: benjamin.dudson@york.ac.uk
Maintainer: Peter Hill
Maintainer-email: peter.hill@york.ac.uk
License: GPLv3
Platform: UNKNOWN
Classifier: Development Status :: 3 - Alpha
Classifier: Environment :: X11 Applications :: Qt
Classifier: Intended Audience :: Science/Research
Classifier: License :: OSI Approved :: GNU General Public License v3 (GPLv3)
Classifier: Programming Language :: Python :: 3
Classifier: Programming Language :: Python :: 3.6
Classifier: Programming Language :: Python :: 3.7
Classifier: Programming Language :: Python :: 3.8
Classifier: Programming Language :: Python :: 3.9
Classifier: Topic :: Scientific/Engineering :: Physics
Classifier: Topic :: Scientific/Engineering :: Visualization
License-File: COPYING
Requires-Dist: matplotlib (>=3.1)
Requires-Dist: numpy (>=1.15)
Requires-Dist: scipy (>=1.4)
Requires-Dist: Qt.py (>=1.2)
Requires-Dist: xdg (>=4.0.1)
Provides-Extra: qt
Requires-Dist: PyQt5 (>=5.15.4) ; extra == 'qt'
Provides-Extra: tests
Requires-Dist: pytest (>=3.3.0) ; extra == 'tests'
Requires-Dist: pytest-cov (>=2.12.1) ; extra == 'tests'
Requires-Dist: pytest-qt (>=4.0.2) ; extra == 'tests'
